acquiring/__init__.py
acquiring/apps.py
acquiring/enums.py
acquiring/settings.py
acquiring/utils.py
acquiring/contrib/__init__.py
acquiring/contrib/paypal/__init__.py
acquiring/contrib/paypal/adapter.py
acquiring/contrib/paypal/domain.py
acquiring/contrib/paypal/blocks/__init__.py
acquiring/contrib/paypal/blocks/paypal_after_creating_order.py
acquiring/contrib/paypal/blocks/paypal_create_order.py
acquiring/domain/__init__.py
acquiring/domain/blocks.py
acquiring/domain/decision_logic.py
acquiring/domain/events.py
acquiring/domain/payments.py
acquiring/domain/providers.py
acquiring/domain/sagas.py
acquiring/protocols/__init__.py
acquiring/protocols/events.py
acquiring/protocols/payments.py
acquiring/protocols/providers.py
acquiring/protocols/storage.py
acquiring/storage/__init__.py
acquiring/storage/django/__init__.py
acquiring/storage/django/models.py
acquiring/storage/django/repositories.py
acquiring/storage/django/unit_of_work.py
acquiring/storage/django/migrations/0001_initial.py
acquiring/storage/django/migrations/__init__.py
acquiring/storage/sqlalchemy/__init__.py
acquiring/storage/sqlalchemy/models.py
acquiring/storage/sqlalchemy/repositories.py
acquiring/storage/sqlalchemy/unit_of_work.py
acquiring/storage/sqlalchemy/migrations/env.py
acquiring/storage/sqlalchemy/migrations/script.py.mako
acquiring/storage/sqlalchemy/migrations/versions/87b793f35b89_add_acquiring_models.py
acquiring-0.4.3.dist-info/LICENSE
acquiring-0.4.3.dist-info/WHEEL
acquiring-0.4.3.dist-info/METADATA
acquiring-0.4.3.dist-info/RECORD
