Metadata-Version: 2.1
Name: acquiring
Version: 0.4.3
Summary: Payment Orchestration Library for Python
Author-email: Alvaro Duran <alvaro.duranb@hotmail.com>
Requires-Python: >=3.8
Classifier: Development Status :: 1 - Planning
Classifier: Environment :: Web Environment
Classifier: Framework :: Django
Classifier: Intended Audience :: Developers
Classifier: Intended Audience :: Financial and Insurance Industry
Classifier: License :: OSI Approved :: MIT License
Classifier: Natural Language :: English
Classifier: Operating System :: OS Independent
Classifier: Programming Language :: Python :: 3 :: Only
Classifier: Topic :: Office/Business :: Financial :: Point-Of-Sale
Classifier: Topic :: Software Development :: Libraries :: Python Modules
Classifier: Typing :: Typed
Requires-Dist: deal >3.2.0
Requires-Dist: requests
Requires-Dist: django>=4.2 ; extra == "django"
Requires-Dist: sqlalchemy>=1.4 ; extra == "sqlalchemy"
Project-URL: Home, https://github.com/acquiringlabs/acquiring
Provides-Extra: django
Provides-Extra: sqlalchemy
